CommanderSnek-0.1.dist-info/DESCRIPTION.rst
CommanderSnek-0.1.dist-info/METADATA
CommanderSnek-0.1.dist-info/RECORD
CommanderSnek-0.1.dist-info/WHEEL
CommanderSnek-0.1.dist-info/metadata.json
CommanderSnek-0.1.dist-info/top_level.txt
Pycom/Command.py
Pycom/Pycom.py
Pycom/__init__.py
